ModuloRiemann/ModuloRiemann.py
ModuloRiemann/__init__.py
moduloriemann-0.0.1.dist-info/METADATA
moduloriemann-0.0.1.dist-info/WHEEL
moduloriemann-0.0.1.dist-info/licenses/LICENSE
moduloriemann-0.0.1.dist-info/RECORD
