Metadata-Version: 2.1
Name: ModuloRiemann
Version: 0.0.1
Summary: Pauqete para realizar sumas de Riemann hacia adelante
Author-email: MiyerEraso <miyer.rosero@udea.edu.co>
License-File: LICENSE
Classifier: License :: OSI Approved :: MIT License
Classifier: Operating System :: OS Independent
Classifier: Programming Language :: Python :: 3
Requires-Python: >=3.7
